auth0_component/__init__.py
auth0_component/frontend/dist/index.html
auth0_component/frontend/dist/assets/index.04b0338d.js
auth0_component/frontend/dist/assets/index.90c573b3.css
garrett_streamlit_auth0-0.9.dist-info/LICENSE
garrett_streamlit_auth0-0.9.dist-info/METADATA
garrett_streamlit_auth0-0.9.dist-info/WHEEL
garrett_streamlit_auth0-0.9.dist-info/top_level.txt
garrett_streamlit_auth0-0.9.dist-info/RECORD
