Metadata-Version: 2.1
Name: garrett-streamlit-auth0
Version: 0.9
Home-page: https://github.com/chris-garrett/garrett-streamlit-auth0
Author: 
Author-email: 
Requires-Python: >=3.6
License-File: LICENSE
Requires-Dist: streamlit >=0.63
Requires-Dist: python-jose ==3.3.0
Requires-Dist: six
